dtfwpy/api/__init__.py
dtfwpy/api/applications/__init__.py
dtfwpy/api/applications/main.py
dtfwpy/api/applications/sub.py
dtfwpy/api/middlewares/__init__.py
dtfwpy/api/middlewares/http_exception.py
dtfwpy/api/middlewares/runtime.py
dtfwpy/api/middlewares/validation_exception.py
dtfwpy/api/routes/__init__.py
dtfwpy/api/routes/authentication.py
dtfwpy/api/routes/response.py
dtfwpy/api/routes/route.py
dtfwpy/api/routes/router.py
dtfwpy/api/schemas/__init__.py
dtfwpy/api/schemas/models.py
dtfwpy/bucket/__init__.py
dtfwpy/bucket/bucket.py
dtfwpy/core/__init__.py
dtfwpy/core/async.py
dtfwpy/core/chunking.py
dtfwpy/core/enums.py
dtfwpy/core/env.py
dtfwpy/core/exception.py
dtfwpy/core/file_folder.py
dtfwpy/core/hashing.py
dtfwpy/core/jsonable_encoder.py
dtfwpy/core/request.py
dtfwpy/core/require_extra.py
dtfwpy/core/retry.py
dtfwpy/core/safe_access.py
dtfwpy/core/singleton.py
dtfwpy/core/slug.py
dtfwpy/core/url.py
dtfwpy/core/validation.py
dtfwpy/database/__init__.py
dtfwpy/database/config.py
dtfwpy/database/database.py
dtfwpy/database/health.py
dtfwpy/database/model.py
dtfwpy/database/search.py
dtfwpy/database/utils.py
dtfwpy/ftp/__init__.py
dtfwpy/ftp/client.py
dtfwpy/log/__init__.py
dtfwpy/log/api_handler.py
dtfwpy/log/config.py
dtfwpy/log/footprint.py
dtfwpy/log/formatter.py
dtfwpy/log/handlers.py
dtfwpy/log/initializer.py
dtfwpy/redis/__init__.py
dtfwpy/redis/caching.py
dtfwpy/redis/config.py
dtfwpy/redis/connection.py
dtfwpy/redis/health.py
dtfwpy/security/__init__.py
dtfwpy/security/encryption.py
dtfwpy/security/hashing.py
dtfwpy/streamer/__init__.py
dtfwpy/streamer/consumer.py
dtfwpy/streamer/sender.py
dtfwpy/worker/__init__.py
dtfwpy/worker/task.py
dtfwpy/worker/worker.py
dtfwpy-0.0.1.dist-info/METADATA
dtfwpy-0.0.1.dist-info/WHEEL
dtfwpy-0.0.1.dist-info/RECORD
